[
  {
    "title": "codeDeck",
    "img": "codeDeck.JPG",
    "descriptionPartial": "codeDeck",
    "demoUrl": "https://median-man.github.io/codeDeck/",
    "repoUrl": "https://github.com/median-man/codeDeck",
    "date": "September 2017"
  },
  {
    "title": "Train Scheduler",
    "img": "trainScheduler.JPG",
    "descriptionPartial": "trainScheduler",
    "demoUrl": "https://median-man.github.io/Train-Scheduler/",
    "repoUrl": "https://github.com/median-man/Train-Scheduler",
    "date": "September 2017"

  },
  {
    "title": "Board Game Trivia",
    "img": "trivia.JPG",
    "descriptionPartial": "triviaGame",
    "demoUrl": "https://median-man.github.io/TriviaGame/",
    "repoUrl": "https://github.com/median-man/TriviaGame",
    "date": "August 2017"
  },
  {
    "title": "Hangman: National Parks",
    "img": "hangmanNP.JPG",
    "descriptionPartial": "hangmanNP",
    "demoUrl": "https://median-man.github.io/Hangman-National-Parks/",
    "repoUrl": "https://github.com/median-man/Hangman-National-Parks",
    "date": "August 2017"
  },
  {
    "title": "Gif-Tastic Gallery",
    "img": "giftastic.JPG",
    "descriptionPartial": "giftastic",
    "demoUrl": "https://median-man.github.io/Gif-Tastic-Gallery/",
    "repoUrl": "https://github.com/median-man/Gif-Tastic-Gallery",
    "date": "August 2017"
  },
  {
    "title": "Eat-Da-Burger",
    "img": "burger.JPG",
    "descriptionPartial": "eatDaBurger",
    "demoUrl": "https://eat-da-burgs.herokuapp.com/",
    "repoUrl": "https://github.com/median-man/Eat-Da-Burger",
    "date": "September 2017"
  }
]